{"v":1,"lamport":23,"ops":[{"kind":"append_entry","text":"{\"config\":{\"cell\":\"ledger\",\"e002_adapter\":\"/Users/yasyf/Code/cc-steer-lab/adapters/watcher-lora-e8-winner\",\"e002_threshold\":0.1533203125,\"render_version\":2},\"config_hash\":\"c1c5fde8e7bc\",\"dataset_digest\":\"a2229be045d1aab3\",\"experiment\":\"E13-dual-shadow\",\"metrics\":{\"agree\":11,\"disagree\":2,\"e002_fired\":0,\"n_buffer_relative\":6,\"n_faithful\":13,\"n_proposals\":19,\"v001_fired\":3},\"seed\":1729,\"verdict\":\"E13 ledger built: 19 proposals (13 faithful scored, 6 buffer_relative carried with null e002). v001 fired 3/19 (recorded); 002 fired 0/13 faithful; arms agree on fire 11/13 faithful, disagree 2. Ledger /Users/yasyf/Code/cc-steer-lab/results/E13/ledger.db.\"}"}]}