{"v":1,"lamport":1,"ops":[{"kind":"create_task","nonce":"f2619765a3d900eef492f9ae90b8a2f7","title":"cc-steer P1: mirror-mode live plumbing (LiveConfig/Mailbox/TeeDelivery, livehook.py fail-open, span scrubber, kill switch, live/inbox CLI)","description":"","type":"task","priority":2,"branch":"main","parent":"","labels":["cc-steer-plan"]},{"kind":"add_criterion","id":"7e7068701b54a2116bf6de0bb9293e9e","text":"canary session passes (model sees steer, scrubber excludes it, authored reply survives mining); kill-switch drill green; codex security review done","script":""}]}