{"v":1,"lamport":1,"ops":[{"kind":"create_task","nonce":"790d7ba46368cbce67bc420d3c959920","title":"retrain cutover rollout: reinstall launchd agents BEFORE Sunday 2026-07-19 04:00","description":"The production training loop moved from cc-steer-lab into the cc-steer package (`cc_steer/retrain/`, `cc-steer retrain --component gate|watcher`, Tinker-backed watcher lane). Once `harness/retrain.py` is deleted from the lab (Phase 5; lab pre-deletion snapshot: cc-steer-lab git commit ad14259), the existing `com.cc-steer.retrain` plist still points at the deleted lab module and will fail Sunday 04:00.\n\nRollout order (Phase 6 of the approved plan):\n1. Soak: manual foreground `cc-steer retrain --component gate` then `--component watcher` on a local editable install (real Tinker spend ~$8-15, user-gated).\n2. Migrate frozen evals: lab `dataset/frozen/gate_eval.parquet` + `dataset/frozen_v2/watcher_eval.parquet` → `~/.cc-steer/eval/`; seed v001 probs via `cc-steer retrain --component watcher --seed-incumbent-probs \u003clab\u003e/results/E11/probs/v001.json`.\n3. Reinstall agents (`cc-steer pipeline install-launchd`) — the retrain prefix must resolve the `retrain` extra (auto-rewritten to `uvx --from 'cc-steer[retrain]' cc-steer` for the default prefix). Smoke the EXACT plist command before trusting the schedule.\n4. Tag the PyPI release after the soak.\n\n⚠️ Serving behavior change at reinstall: the watch agent's plist previously hardcoded `--gate-threshold 0.5`, overriding the promoted gate's trained threshold (v001: 0.9935). The new agents honor the promoted metadata threshold — surface this to the user at the gate.\n\nAlso: reconcile cc-notes task 41f08fd (P5 watcher improve-loop) — this consolidation delivers its train_watcher/weekly-launchd/auto-promote scope in the package instead of the lab.","type":"task","priority":1,"branch":"","parent":"","labels":["cc-steer","rollout","retrain-cutover"]},{"kind":"add_criterion","id":"3c2f3066fa4ab5bf0a863fe9b05d8912","text":"com.cc-steer.retrain plist runs the package CLI (no lab reference) and its exact command was smoke-tested","script":""},{"kind":"add_criterion","id":"be3782d90899bd2c03fc381f118b6047","text":"manual gate+watcher soak runs completed with verdict lines in retrain.log and journal entries in ~/.cc-steer/retrain/journal.jsonl","script":""},{"kind":"add_criterion","id":"ac507436459045661d4696a33aaf4bb6","text":"frozen evals + v001 incumbent probs present under ~/.cc-steer/eval/ with digest verification passing","script":""},{"kind":"add_criterion","id":"0b47edc7286164c096c93e45e8dc115e","text":"user acknowledged the gate-threshold serving change (hardcoded 0.5 dropped in favor of promoted metadata threshold)","script":""},{"kind":"add_criterion","id":"8a934965372a921e74736326f328f39c","text":"cc-notes task 41f08fd reconciled against the delivered package retrain loop","script":""}]}